x_cli_py/__init__.py
x_cli_py/commands/__init__.py
x_cli_py/commands/post.py
x_cli_py/commands/setup.py
x_cli_py/commands/timeline.py
x_cli_py/commands/whoami.py
x_cli_py/main.py
x_cli_py/theme.py
x_cli_py/xcli.py
x_cli_py-0.1.4.dist-info/LICENSE
x_cli_py-0.1.4.dist-info/METADATA
x_cli_py-0.1.4.dist-info/WHEEL
x_cli_py-0.1.4.dist-info/entry_points.txt
x_cli_py-0.1.4.dist-info/RECORD
