Metadata-Version: 2.3
Name: x-cli-py
Version: 0.1.4
Summary: An unofficial CLI tool for x.com
License: LICENSE
Author: tuesdayjz
Author-email: moka010302@gmail.com
Requires-Python: >=3.12
Classifier: License :: Other/Proprietary License
Classifier: Programming Language :: Python :: 3
Classifier: Programming Language :: Python :: 3.12
Classifier: Programming Language :: Python :: 3.13
Requires-Dist: rich (>=13.9.4,<14.0.0)
Requires-Dist: selenium (>=4.29.0,<5.0.0)
Requires-Dist: typer (>=0.15.2,<0.16.0)
